PyBVMT.py
fetchapi.py
PyBVMT-1.0.0.dist-info/LICENSE
PyBVMT-1.0.0.dist-info/METADATA
PyBVMT-1.0.0.dist-info/WHEEL
PyBVMT-1.0.0.dist-info/top_level.txt
PyBVMT-1.0.0.dist-info/RECORD
