Metadata-Version: 2.1
Name: PyBVMT
Version: 1.0.0
Summary: BVMT API
Home-page: UNKNOWN
Author: NAOUALI Nebil
Author-email: elnaoualinebil@gmail.com
License: MIT
Download-URL: https://github.com/Naouali/pyBVMT/archive/pyBVMT.tar.gz
Platform: UNKNOWN
Classifier: Programming Language :: Python :: 3.6
Classifier: Programming Language :: Python :: 3.7
Classifier: License :: OSI Approved :: MIT License
Classifier: Operating System :: OS Independent
Requires-Python: >=3.5
Requires-Dist: pandas (>=1.0.0)
Requires-Dist: requests (>=2.20.0)
Requires-Dist: matplotlib (>=3.0.0)
Provides-Extra: dev
Requires-Dist: pandas ; extra == 'dev'
Requires-Dist: requests ; extra == 'dev'
